{
	"configurations" : 
	[
		{
			"directories" : 
			[
				{
					"build" : ".",
					"childIndexes" : 
					[
						1,
						4
					],
					"hasInstallRule" : true,
					"jsonFile" : "directory-.-Debug-d0094a50bb2071803777.json",
					"minimumCMakeVersion" : 
					{
						"string" : "3.13"
					},
					"projectIndex" : 0,
					"source" : ".",
					"targetIndexes" : 
					[
						0,
						1
					]
				},
				{
					"build" : "googletest",
					"childIndexes" : 
					[
						2
					],
					"hasInstallRule" : true,
					"jsonFile" : "directory-googletest-Debug-294c64d4885f2a55f3f7.json",
					"minimumCMakeVersion" : 
					{
						"string" : "3.5"
					},
					"parentIndex" : 0,
					"projectIndex" : 1,
					"source" : "googletest"
				},
				{
					"build" : "googletest/googlemock",
					"childIndexes" : 
					[
						3
					],
					"hasInstallRule" : true,
					"jsonFile" : "directory-googletest.googlemock-Debug-93605e70d2d38b8009da.json",
					"minimumCMakeVersion" : 
					{
						"string" : "3.5"
					},
					"parentIndex" : 1,
					"projectIndex" : 2,
					"source" : "googletest/googlemock",
					"targetIndexes" : 
					[
						2,
						3
					]
				},
				{
					"build" : "googletest/googletest",
					"hasInstallRule" : true,
					"jsonFile" : "directory-googletest.googletest-Debug-ba87a2cbd026a224628a.json",
					"minimumCMakeVersion" : 
					{
						"string" : "3.5"
					},
					"parentIndex" : 2,
					"projectIndex" : 3,
					"source" : "googletest/googletest",
					"targetIndexes" : 
					[
						4,
						5
					]
				},
				{
					"build" : "test",
					"jsonFile" : "directory-test-Debug-f18be1977b403cfd1a50.json",
					"minimumCMakeVersion" : 
					{
						"string" : "3.13"
					},
					"parentIndex" : 0,
					"projectIndex" : 4,
					"source" : "test",
					"targetIndexes" : 
					[
						6
					]
				}
			],
			"name" : "Debug",
			"projects" : 
			[
				{
					"childIndexes" : 
					[
						1,
						4
					],
					"directoryIndexes" : 
					[
						0
					],
					"name" : "8puzzle",
					"targetIndexes" : 
					[
						0,
						1
					]
				},
				{
					"childIndexes" : 
					[
						2
					],
					"directoryIndexes" : 
					[
						1
					],
					"name" : "googletest-distribution",
					"parentIndex" : 0
				},
				{
					"childIndexes" : 
					[
						3
					],
					"directoryIndexes" : 
					[
						2
					],
					"name" : "gmock",
					"parentIndex" : 1,
					"targetIndexes" : 
					[
						2,
						3
					]
				},
				{
					"directoryIndexes" : 
					[
						3
					],
					"name" : "gtest",
					"parentIndex" : 2,
					"targetIndexes" : 
					[
						4,
						5
					]
				},
				{
					"directoryIndexes" : 
					[
						4
					],
					"name" : "8puzzle_test",
					"parentIndex" : 0,
					"targetIndexes" : 
					[
						6
					]
				}
			],
			"targets" : 
			[
				{
					"directoryIndex" : 0,
					"id" : "8puzzle::@6890427a1f51a3e7e1df",
					"jsonFile" : "target-8puzzle-Debug-a06a79fa5f528279a610.json",
					"name" : "8puzzle",
					"projectIndex" : 0
				},
				{
					"directoryIndex" : 0,
					"id" : "8puzzle_lib::@6890427a1f51a3e7e1df",
					"jsonFile" : "target-8puzzle_lib-Debug-a0c5e5c1871d7d1dd55c.json",
					"name" : "8puzzle_lib",
					"projectIndex" : 0
				},
				{
					"directoryIndex" : 2,
					"id" : "gmock::@d68da25237a7ca2351af",
					"jsonFile" : "target-gmock-Debug-f1c9c809ef3d84b1ee84.json",
					"name" : "gmock",
					"projectIndex" : 2
				},
				{
					"directoryIndex" : 2,
					"id" : "gmock_main::@d68da25237a7ca2351af",
					"jsonFile" : "target-gmock_main-Debug-fef449993770a399c5e8.json",
					"name" : "gmock_main",
					"projectIndex" : 2
				},
				{
					"directoryIndex" : 3,
					"id" : "gtest::@f95b5c00bd49b3b4698d",
					"jsonFile" : "target-gtest-Debug-f21901c051407ef8243d.json",
					"name" : "gtest",
					"projectIndex" : 3
				},
				{
					"directoryIndex" : 3,
					"id" : "gtest_main::@f95b5c00bd49b3b4698d",
					"jsonFile" : "target-gtest_main-Debug-11aa47a65eaf31abc90b.json",
					"name" : "gtest_main",
					"projectIndex" : 3
				},
				{
					"directoryIndex" : 4,
					"id" : "runUnitTests::@36f028580bb02cc8272a",
					"jsonFile" : "target-runUnitTests-Debug-667de92b1114cbf0d187.json",
					"name" : "runUnitTests",
					"projectIndex" : 4
				}
			]
		}
	],
	"kind" : "codemodel",
	"paths" : 
	{
		"build" : "C:/Users/Ljts/Desktop/hw/sem2/cpp/8puzzle/build",
		"source" : "C:/Users/Ljts/Desktop/hw/sem2/cpp/8puzzle"
	},
	"version" : 
	{
		"major" : 2,
		"minor" : 3
	}
}
